pygeodist/__init__.py
pygeodist/demo.py
pygeodist/main.py
pygeodist/point.py
pygeodist-0.0.1.dist-info/LICENSE
pygeodist-0.0.1.dist-info/METADATA
pygeodist-0.0.1.dist-info/WHEEL
pygeodist-0.0.1.dist-info/top_level.txt
pygeodist-0.0.1.dist-info/RECORD
