Metadata-Version: 2.1
Name: pygeodist
Version: 0.0.1
Summary: A package to calculate the distance between two geographical points using their latitude and longitude coordinates.
Author: Harsh Panchal
License: Copyright (c) 2022 Oxford University Research Software Engineering
Project-URL: Homepage, https://github.com/HarshPanchal18/geodist
Project-URL: Bug Tracker, https://github.com/HarshPanchal18/geodist/issues
Classifier: Programming Language :: Python :: 3
Classifier: License :: OSI Approved :: MIT License
Classifier: Operating System :: OS Independent
Requires-Python: >=3.0
License-File: LICENSE
